Workbook

Sheet Libro de caja
A1: Libro de caja - Escenario A2 (ExtraCash S/ 10,900) - v2 con mantenimiento
A2: Movimientos de tus cuentas de débito. Saldo = saldo anterior + entra - sale.
A4: Fecha | B4: Concepto | C4: Categoría | D4: Entra | E4: Sale | F4: Saldo | H4: Control vs Plan
A5: Octubre 2026
A6: =Supuestos!$B$5 | B6: Saldo inicial (Interbank + BCP) | C6: Saldo | F6: ='Plan mensual'!B5
A7: =Supuestos!$B$5+3 | B7: Desembolso neto ExtraCash (10,900 - 3,430.10 deuda actual) | C7: Préstamo | D7: ='Plan mensual'!D5 | F7: =F6+D7-E7
A8: =Supuestos!$B$5+3 | B8: Pago deuda total tarjeta Visa Infinite | C8: Tarjeta | E8: ='Plan mensual'!F5 | F8: =F7+D8-E8
A9: ='Plan mensual'!$A$5+21 | B9: Prepago ExtraCash (reducir plazo) | C9: Deuda | E9: ='Plan mensual'!J5 | F9: =F8+D9-E9
A10: =EOMONTH('Plan mensual'!$A$5,0) | B10: Supermercado (total del mes) | C10: Gasto de vida | E10: =Supuestos!$C$31 | F10: =F9+D10-E10
A11: =EOMONTH('Plan mensual'!$A$5,0) | B11: Taxis (total del mes) | C11: Gasto de vida | E11: =Supuestos!$C$32 | F11: =F10+D11-E11
A12: =EOMONTH('Plan mensual'!$A$5,0) | B12: Otros (total del mes) | C12: Gasto de vida | E12: =Supuestos!$C$33 | F12: =F11+D12-E12
A13: =EOMONTH('Plan mensual'!$A$5,0) | B13: Contador Luxr (total del mes) | C13: Gasto de vida | E13: =Supuestos!$C$34 | F13: =F12+D13-E13
A14: ='Plan mensual'!$A$5+9 | B14: Mantenimiento + agua (Yape) | C14: Gasto fijo | E14: =IF('Plan mensual'!$A$5<=Supuestos!$B$28,Supuestos!$B$27,0) | F14: =F13+D14-E14
A15: =EOMONTH('Plan mensual'!$A$5,0) | B15: SALDO FINAL DEL MES | C15: ="Apartado tarjeta: S/ "&TEXT('Plan mensual'!H5,"#,##0.00") | F15: =F14 | H15: =IF(ABS(F15-'Plan mensual'!K5)<0.01,"OK","Revisar")
A17: Noviembre 2026
A18: ='Plan mensual'!$A$6-1 | B18: Sueldo Simtryx | C18: Ingreso | D18: ='Plan mensual'!C6 | F18: =F15+D18-E18
A19: ='Plan mensual'!$A$6+14 | B19: Pago estado de cuenta tarjeta (cargos del mes anterior) + pendientes + interés residual | C19: Tarjeta | E19: ='Plan mensual'!F6 | F19: =F18+D19-E19
A20: ='Plan mensual'!$A$6+14 | B20: Cuota ExtraCash | C20: Deuda | E20: ='Plan mensual'!G6 | F20: =F19+D20-E20
A21: ='Plan mensual'!$A$6+21 | B21: Prepago ExtraCash (reducir plazo) | C21: Deuda | E21: ='Plan mensual'!J6 | F21: =F20+D21-E21
A22: =EOMONTH('Plan mensual'!$A$6,0) | B22: Supermercado (total del mes) | C22: Gasto de vida | E22: =Supuestos!$B$31 | F22: =F21+D22-E22
A23: =EOMONTH('Plan mensual'!$A$6,0) | B23: Taxis (total del mes) | C23: Gasto de vida | E23: =Supuestos!$B$32 | F23: =F22+D23-E23
A24: =EOMONTH('Plan mensual'!$A$6,0) | B24: Otros (total del mes) | C24: Gasto de vida | E24: =Supuestos!$B$33 | F24: =F23+D24-E24
A25: =EOMONTH('Plan mensual'!$A$6,0) | B25: Contador Luxr (total del mes) | C25: Gasto de vida | E25: =Supuestos!$B$34 | F25: =F24+D25-E25
A26: ='Plan mensual'!$A$6+9 | B26: Mantenimiento + agua (Yape) | C26: Gasto fijo | E26: =IF('Plan mensual'!$A$6<=Supuestos!$B$28,Supuestos!$B$27,0) | F26: =F25+D26-E26
A27: =EOMONTH('Plan mensual'!$A$6,0) | B27: SALDO FINAL DEL MES | C27: ="Apartado tarjeta: S/ "&TEXT('Plan mensual'!H6,"#,##0.00") | F27: =F26 | H27: =IF(ABS(F27-'Plan mensual'!K6)<0.01,"OK","Revisar")
A29: Diciembre 2026
A30: ='Plan mensual'!$A$7-1 | B30: Sueldo Simtryx | C30: Ingreso | D30: ='Plan mensual'!C7 | F30: =F27+D30-E30
A31: ='Plan mensual'!$A$7+14 | B31: Pago estado de cuenta tarjeta (cargos del mes anterior) | C31: Tarjeta | E31: ='Plan mensual'!F7 | F31: =F30+D31-E31
A32: ='Plan mensual'!$A$7+14 | B32: Cuota ExtraCash | C32: Deuda | E32: ='Plan mensual'!G7 | F32: =F31+D32-E32
A33: ='Plan mensual'!$A$7+21 | B33: Prepago ExtraCash (reducir plazo) | C33: Deuda | E33: ='Plan mensual'!J7 | F33: =F32+D33-E33
A34: =EOMONTH('Plan mensual'!$A$7,0) | B34: Supermercado (total del mes) | C34: Gasto de vida | E34: =Supuestos!$B$31 | F34: =F33+D34-E34
A35: =EOMONTH('Plan mensual'!$A$7,0) | B35: Taxis (total del mes) | C35: Gasto de vida | E35: =Supuestos!$B$32 | F35: =F34+D35-E35
A36: =EOMONTH('Plan mensual'!$A$7,0) | B36: Otros (total del mes) | C36: Gasto de vida | E36: =Supuestos!$B$33 | F36: =F35+D36-E36
A37: =EOMONTH('Plan mensual'!$A$7,0) | B37: Contador Luxr (total del mes) | C37: Gasto de vida | E37: =Supuestos!$B$34 | F37: =F36+D37-E37
A38: ='Plan mensual'!$A$7+9 | B38: Mantenimiento + agua (Yape) | C38: Gasto fijo | E38: =IF('Plan mensual'!$A$7<=Supuestos!$B$28,Supuestos!$B$27,0) | F38: =F37+D38-E38
A39: =EOMONTH('Plan mensual'!$A$7,0) | B39: SALDO FINAL DEL MES | C39: ="Apartado tarjeta: S/ "&TEXT('Plan mensual'!H7,"#,##0.00") | F39: =F38 | H39: =IF(ABS(F39-'Plan mensual'!K7)<0.01,"OK","Revisar")
A41: Enero 2027
A42: ='Plan mensual'!$A$8-1 | B42: Sueldo Simtryx | C42: Ingreso | D42: ='Plan mensual'!C8 | F42: =F39+D42-E42
A43: ='Plan mensual'!$A$8+14 | B43: Pago estado de cuenta tarjeta (cargos del mes anterior) | C43: Tarjeta | E43: ='Plan mensual'!F8 | F43: =F42+D43-E43
A44: ='Plan mensual'!$A$8+14 | B44: Cuota ExtraCash | C44: Deuda | E44: ='Plan mensual'!G8 | F44: =F43+D44-E44
A45: ='Plan mensual'!$A$8+21 | B45: Prepago ExtraCash (reducir plazo) | C45: Deuda | E45: ='Plan mensual'!J8 | F45: =F44+D45-E45
A46: =EOMONTH('Plan mensual'!$A$8,0) | B46: Supermercado (total del mes) | C46: Gasto de vida | E46: =Supuestos!$B$31 | F46: =F45+D46-E46
A47: =EOMONTH('Plan mensual'!$A$8,0) | B47: Taxis (total del mes) | C47: Gasto de vida | E47: =Supuestos!$B$32 | F47: =F46+D47-E47
A48: =EOMONTH('Plan mensual'!$A$8,0) | B48: Otros (total del mes) | C48: Gasto de vida | E48: =Supuestos!$B$33 | F48: =F47+D48-E48
A49: =EOMONTH('Plan mensual'!$A$8,0) | B49: Contador Luxr (total del mes) | C49: Gasto de vida | E49: =Supuestos!$B$34 | F49: =F48+D49-E49
A50: ='Plan mensual'!$A$8+9 | B50: Mantenimiento + agua (Yape) | C50: Gasto fijo | E50: =IF('Plan mensual'!$A$8<=Supuestos!$B$28,Supuestos!$B$27,0) | F50: =F49+D50-E50
A51: =EOMONTH('Plan mensual'!$A$8,0) | B51: SALDO FINAL DEL MES | C51: ="Apartado tarjeta: S/ "&TEXT('Plan mensual'!H8,"#,##0.00") | F51: =F50 | H51: =IF(ABS(F51-'Plan mensual'!K8)<0.01,"OK","Revisar")
A53: Febrero 2027
A54: ='Plan mensual'!$A$9-1 | B54: Sueldo Simtryx | C54: Ingreso | D54: ='Plan mensual'!C9 | F54: =F51+D54-E54
A55: ='Plan mensual'!$A$9+14 | B55: Pago estado de cuenta tarjeta (cargos del mes anterior) | C55: Tarjeta | E55: ='Plan mensual'!F9 | F55: =F54+D55-E55
A56: ='Plan mensual'!$A$9+14 | B56: Cuota ExtraCash | C56: Deuda | E56: ='Plan mensual'!G9 | F56: =F55+D56-E56
A57: ='Plan mensual'!$A$9+21 | B57: Prepago ExtraCash (reducir plazo) | C57: Deuda | E57: ='Plan mensual'!J9 | F57: =F56+D57-E57
A58: =EOMONTH('Plan mensual'!$A$9,0) | B58: Supermercado (total del mes) | C58: Gasto de vida | E58: =Supuestos!$B$31 | F58: =F57+D58-E58
A59: =EOMONTH('Plan mensual'!$A$9,0) | B59: Taxis (total del mes) | C59: Gasto de vida | E59: =Supuestos!$B$32 | F59: =F58+D59-E59
A60: =EOMONTH('Plan mensual'!$A$9,0) | B60: Otros (total del mes) | C60: Gasto de vida | E60: =Supuestos!$B$33 | F60: =F59+D60-E60
A61: =EOMONTH('Plan mensual'!$A$9,0) | B61: Contador Luxr (total del mes) | C61: Gasto de vida | E61: =Supuestos!$B$34 | F61: =F60+D61-E61
A62: ='Plan mensual'!$A$9+9 | B62: Mantenimiento + agua (Yape) | C62: Gasto fijo | E62: =IF('Plan mensual'!$A$9<=Supuestos!$B$28,Supuestos!$B$27,0) | F62: =F61+D62-E62
A63: =EOMONTH('Plan mensual'!$A$9,0) | B63: SALDO FINAL DEL MES | C63: ="Apartado tarjeta: S/ "&TEXT('Plan mensual'!H9,"#,##0.00") | F63: =F62 | H63: =IF(ABS(F63-'Plan mensual'!K9)<0.01,"OK","Revisar")
A65: Marzo 2027
A66: ='Plan mensual'!$A$10-1 | B66: Sueldo Simtryx | C66: Ingreso | D66: ='Plan mensual'!C10 | F66: =F63+D66-E66
A67: ='Plan mensual'!$A$10+14 | B67: Pago estado de cuenta tarjeta (cargos del mes anterior) | C67: Tarjeta | E67: ='Plan mensual'!F10 | F67: =F66+D67-E67
A68: ='Plan mensual'!$A$10+14 | B68: Cuota ExtraCash | C68: Deuda | E68: ='Plan mensual'!G10 | F68: =F67+D68-E68
A69: ='Plan mensual'!$A$10+21 | B69: Prepago ExtraCash (reducir plazo) | C69: Deuda | E69: ='Plan mensual'!J10 | F69: =F68+D69-E69
A70: =EOMONTH('Plan mensual'!$A$10,0) | B70: Supermercado (total del mes) | C70: Gasto de vida | E70: =Supuestos!$B$31 | F70: =F69+D70-E70
A71: =EOMONTH('Plan mensual'!$A$10,0) | B71: Taxis (total del mes) | C71: Gasto de vida | E71: =Supuestos!$B$32 | F71: =F70+D71-E71
A72: =EOMONTH('Plan mensual'!$A$10,0) | B72: Otros (total del mes) | C72: Gasto de vida | E72: =Supuestos!$B$33 | F72: =F71+D72-E72
A73: =EOMONTH('Plan mensual'!$A$10,0) | B73: Contador Luxr (total del mes) | C73: Gasto de vida | E73: =Supuestos!$B$34 | F73: =F72+D73-E73
A74: ='Plan mensual'!$A$10+9 | B74: Mantenimiento + agua (Yape) | C74: Gasto fijo | E74: =IF('Plan mensual'!$A$10<=Supuestos!$B$28,Supuestos!$B$27,0) | F74: =F73+D74-E74
A75: =EOMONTH('Plan mensual'!$A$10,0) | B75: SALDO FINAL DEL MES | C75: ="Apartado tarjeta: S/ "&TEXT('Plan mensual'!H10,"#,##0.00") | F75: =F74 | H75: =IF(ABS(F75-'Plan mensual'!K10)<0.01,"OK","Revisar")
A77: Abril 2027
A78: ='Plan mensual'!$A$11-1 | B78: Sueldo Simtryx | C78: Ingreso | D78: ='Plan mensual'!C11 | F78: =F75+D78-E78
A79: ='Plan mensual'!$A$11+14 | B79: Pago estado de cuenta tarjeta (cargos del mes anterior) | C79: Tarjeta | E79: ='Plan mensual'!F11 | F79: =F78+D79-E79
A80: ='Plan mensual'!$A$11+14 | B80: Cuota ExtraCash | C80: Deuda | E80: ='Plan mensual'!G11 | F80: =F79+D80-E80
A81: ='Plan mensual'!$A$11+21 | B81: Prepago ExtraCash (reducir plazo) | C81: Deuda | E81: ='Plan mensual'!J11 | F81: =F80+D81-E81
A82: =EOMONTH('Plan mensual'!$A$11,0) | B82: Supermercado (total del mes) | C82: Gasto de vida | E82: =Supuestos!$B$31 | F82: =F81+D82-E82
A83: =EOMONTH('Plan mensual'!$A$11,0) | B83: Taxis (total del mes) | C83: Gasto de vida | E83: =Supuestos!$B$32 | F83: =F82+D83-E83
A84: =EOMONTH('Plan mensual'!$A$11,0) | B84: Otros (total del mes) | C84: Gasto de vida | E84: =Supuestos!$B$33 | F84: =F83+D84-E84
A85: =EOMONTH('Plan mensual'!$A$11,0) | B85: Contador Luxr (total del mes) | C85: Gasto de vida | E85: =Supuestos!$B$34 | F85: =F84+D85-E85
A86: ='Plan mensual'!$A$11+9 | B86: Mantenimiento + agua (Yape) | C86: Gasto fijo | E86: =IF('Plan mensual'!$A$11<=Supuestos!$B$28,Supuestos!$B$27,0) | F86: =F85+D86-E86
A87: =EOMONTH('Plan mensual'!$A$11,0) | B87: SALDO FINAL DEL MES | C87: ="Apartado tarjeta: S/ "&TEXT('Plan mensual'!H11,"#,##0.00") | F87: =F86 | H87: =IF(ABS(F87-'Plan mensual'!K11)<0.01,"OK","Revisar")
A89: Mayo 2027
A90: ='Plan mensual'!$A$12-1 | B90: Sueldo Simtryx | C90: Ingreso | D90: ='Plan mensual'!C12 | F90: =F87+D90-E90
A91: ='Plan mensual'!$A$12+14 | B91: Pago estado de cuenta tarjeta (cargos del mes anterior) | C91: Tarjeta | E91: ='Plan mensual'!F12 | F91: =F90+D91-E91
A92: ='Plan mensual'!$A$12+14 | B92: Cuota ExtraCash | C92: Deuda | E92: ='Plan mensual'!G12 | F92: =F91+D92-E92
A93: ='Plan mensual'!$A$12+21 | B93: Prepago ExtraCash (reducir plazo) | C93: Deuda | E93: ='Plan mensual'!J12 | F93: =F92+D93-E93
A94: =EOMONTH('Plan mensual'!$A$12,0) | B94: Supermercado (total del mes) | C94: Gasto de vida | E94: =Supuestos!$B$31 | F94: =F93+D94-E94
A95: =EOMONTH('Plan mensual'!$A$12,0) | B95: Taxis (total del mes) | C95: Gasto de vida | E95: =Supuestos!$B$32 | F95: =F94+D95-E95
A96: =EOMONTH('Plan mensual'!$A$12,0) | B96: Otros (total del mes) | C96: Gasto de vida | E96: =Supuestos!$B$33 | F96: =F95+D96-E96
A97: =EOMONTH('Plan mensual'!$A$12,0) | B97: Contador Luxr (total del mes) | C97: Gasto de vida | E97: =Supuestos!$B$34 | F97: =F96+D97-E97
A98: ='Plan mensual'!$A$12+9 | B98: Mantenimiento + agua (Yape) | C98: Gasto fijo | E98: =IF('Plan mensual'!$A$12<=Supuestos!$B$28,Supuestos!$B$27,0) | F98: =F97+D98-E98
A99: =EOMONTH('Plan mensual'!$A$12,0) | B99: SALDO FINAL DEL MES | C99: ="Apartado tarjeta: S/ "&TEXT('Plan mensual'!H12,"#,##0.00") | F99: =F98 | H99: =IF(ABS(F99-'Plan mensual'!K12)<0.01,"OK","Revisar")
A101: Junio 2027
A102: ='Plan mensual'!$A$13-1 | B102: Sueldo Simtryx | C102: Ingreso | D102: ='Plan mensual'!C13 | F102: =F99+D102-E102
A103: ='Plan mensual'!$A$13+14 | B103: Pago estado de cuenta tarjeta (cargos del mes anterior) | C103: Tarjeta | E103: ='Plan mensual'!F13 | F103: =F102+D103-E103
A104: ='Plan mensual'!$A$13+14 | B104: Cuota ExtraCash | C104: Deuda | E104: ='Plan mensual'!G13 | F104: =F103+D104-E104
A105: ='Plan mensual'!$A$13+21 | B105: Prepago ExtraCash (reducir plazo) | C105: Deuda | E105: ='Plan mensual'!J13 | F105: =F104+D105-E105
A106: =EOMONTH('Plan mensual'!$A$13,0) | B106: Supermercado (total del mes) | C106: Gasto de vida | E106: =Supuestos!$B$31 | F106: =F105+D106-E106
A107: =EOMONTH('Plan mensual'!$A$13,0) | B107: Taxis (total del mes) | C107: Gasto de vida | E107: =Supuestos!$B$32 | F107: =F106+D107-E107
A108: =EOMONTH('Plan mensual'!$A$13,0) | B108: Otros (total del mes) | C108: Gasto de vida | E108: =Supuestos!$B$33 | F108: =F107+D108-E108
A109: =EOMONTH('Plan mensual'!$A$13,0) | B109: Contador Luxr (total del mes) | C109: Gasto de vida | E109: =Supuestos!$B$34 | F109: =F108+D109-E109
...

Sheet Supuestos
A1: Supuestos - Libro de caja escenario A2
A2: Azul = dato editable. Amarillo = estimado, reemplazar con el dato real cuando lo tengas.
A4: Efectivo y fechas
A5: Fecha inicio | B5: 46300 | C5: Hoy
A6: Saldo cuenta Interbank | B6: 2266.99 | C6: Dato del usuario, 05/10/2026
A7: Saldo cuenta BCP | B7: 482.06 | C7: Dato del usuario, 05/10/2026. Transferir a Interbank
A8: Sueldo neto mensual (llega fin de mes) | B8: 4600 | C8: Simtryx, recibos por honorarios
A9: ExtraCash nuevo (absorbe el actual)
A10: Monto ExtraCash | B10: 10900 | C10: Máximo ofrecido por la app
A11: Deuda ExtraCash actual a cancelar | B11: 3430.1 | C11: Pantalla de confirmación de la app
A12: Factor importe financiado / monto | B12: 1.00514 | C12: App: 9,046.26 financiado por 9,000 (interés hasta 1ª cuota)
A13: Cuota mensual (24 meses) | B13: 534.56 | C13: Confirmado en la app Interbank (simulación 10,900 a 24 meses)
A14: TEA | B14: 0.1663 | C14: App Interbank
A15: Seguro desgravamen incluido en la cuota | B15: 3.55 | C15: Estimado (cuota app - cuota financiera)
A16: Monto a recibir | B16: =Supuestos!$B$10-Supuestos!$B$11
A17: Importe financiado | B17: =Supuestos!$B$10*Supuestos!$B$12
A18: TEM | B18: =(1+Supuestos!$B$14)^(1/12)-1
A19: Tarjeta Visa Infinite
A20: Deuda total tarjeta (a pagar con el préstamo) | B20: 8791.82 | C20: App, pestaña Deuda total
A21: Consumido tarjeta | B21: 8992.74 | C21: App
A22: Cargos pendientes (aparecen en el estado del 21/10) | B22: =Supuestos!$B$21-Supuestos!$B$20
A23: Interés residual + seguro (estado 21/10) | B23: 275 | C23: Estimado. Reemplazar con el estado de cuenta real
A24: Servicios a la tarjeta (luz, gas, internet, celular, Interseguro) | B24: 346.5 | C24: 313 + 33.50, estado de cuenta
A25: Pensión PUCP (a la tarjeta) | B25: 815 | C25: Estado de cuenta
A26: Último mes de pensión | B26: 46357 | C26: Usuario: hasta fin de año
A27: Mantenimiento + agua del edificio (débito) | B27: 197 | C27: Usuario 11/10/2026: se paga cada mes hasta diciembre
A28: Último mes de mantenimiento | B28: 46357 | C28: Usuario: hasta diciembre (mudanza)
A29: Gastos de vida con débito (mes completo)
A30: Rubro | B30: Mes completo | C30: Octubre (desde el 05/10)
A31: Supermercado | B31: 500 | C31: 400
A32: Taxis | B32: 300 | C32: 225
A33: Otros | B33: 200 | C33: 120
A34: Contador Luxr | B34: 150 | C34: 150
A36: Notas:
A37: - Regla: la tarjeta solo carga servicios fijos y se paga completa el 15 del mes siguiente.
A38: - Cada mes se aparta en caja lo cargado a la tarjeta ese mes. El resto va a prepago (reducir plazo).
A39: - El interés del ExtraCash se aproxima con TEM sobre el saldo de inicio de mes.

Sheet Plan mensual
A1: Plan mensual - caja y deuda
A2: Todo se calcula desde Supuestos. Caja = cuentas de débito (Interbank + BCP).
A4: Mes | B4: Caja inicial | C4: Sueldo | D4: Desembolso neto | E4: Gastos de vida | F4: Pago tarjeta | G4: Cuota ExtraCash | H4: Cargos a tarjeta del mes (apartar) | I4: Disponible para prepago | J4: Prepago | K4: Caja final | L4: ExtraCash saldo inicial | M4: Interés | N4: Seguro | O4: ExtraCash saldo final | P4: Intereses acumulados
A5: =DATE(YEAR(Supuestos!$B$5),MONTH(Supuestos!$B$5),1) | B5: =Supuestos!$B$6+Supuestos!$B$7 | C5: =0 | D5: =Supuestos!$B$16 | E5: =Supuestos!$C$31+Supuestos!$C$32+Supuestos!$C$33+Supuestos!$C$34+IF(A5<=Supuestos!$B$28,Supuestos!$B$27,0) | F5: =Supuestos!$B$20 | G5: =IF(L5>0.01,MIN(Supuestos!$B$13,L5+M5+N5),0) | H5: =Supuestos!$B$24+IF(A5<=Supuestos!$B$26,Supuestos!$B$25,0) | I5: =B5+C5+D5-E5-F5-G5-H5 | J5: =MAX(0,MIN(I5,L5+M5+N5-G5)) | K5: =B5+C5+D5-E5-F5-G5-J5 | L5: =0 | M5: =L5*Supuestos!$B$18 | N5: =IF(L5>0.01,Supuestos!$B$15,0) | O5: =Supuestos!$B$17 | P5: =M5
A6: =DATE(YEAR(A5),MONTH(A5)+1,1) | B6: =K5 | C6: =Supuestos!$B$8 | D6: =0 | E6: =Supuestos!$B$31+Supuestos!$B$32+Supuestos!$B$33+Supuestos!$B$34+IF(A6<=Supuestos!$B$28,Supuestos!$B$27,0) | F6: =H5+Supuestos!$B$22+Supuestos!$B$23 | G6: =IF(L6>0.01,MIN(Supuestos!$B$13,L6+M6+N6),0) | H6: =Supuestos!$B$24+IF(A6<=Supuestos!$B$26,Supuestos!$B$25,0) | I6: =B6+C6+D6-E6-F6-G6-H6 | J6: =MAX(0,MIN(I6,L6+M6+N6-G6)) | K6: =B6+C6+D6-E6-F6-G6-J6 | L6: =O5 | M6: =L6*Supuestos!$B$18 | N6: =IF(L6>0.01,Supuestos!$B$15,0) | O6: =L6+M6+N6-G6-J6 | P6: =P5+M6
A7: =DATE(YEAR(A6),MONTH(A6)+1,1) | B7: =K6 | C7: =Supuestos!$B$8 | D7: =0 | E7: =Supuestos!$B$31+Supuestos!$B$32+Supuestos!$B$33+Supuestos!$B$34+IF(A7<=Supuestos!$B$28,Supuestos!$B$27,0) | F7: =H6 | G7: =IF(L7>0.01,MIN(Supuestos!$B$13,L7+M7+N7),0) | H7: =Supuestos!$B$24+IF(A7<=Supuestos!$B$26,Supuestos!$B$25,0) | I7: =B7+C7+D7-E7-F7-G7-H7 | J7: =MAX(0,MIN(I7,L7+M7+N7-G7)) | K7: =B7+C7+D7-E7-F7-G7-J7 | L7: =O6 | M7: =L7*Supuestos!$B$18 | N7: =IF(L7>0.01,Supuestos!$B$15,0) | O7: =L7+M7+N7-G7-J7 | P7: =P6+M7
A8: =DATE(YEAR(A7),MONTH(A7)+1,1) | B8: =K7 | C8: =Supuestos!$B$8 | D8: =0 | E8: =Supuestos!$B$31+Supuestos!$B$32+Supuestos!$B$33+Supuestos!$B$34+IF(A8<=Supuestos!$B$28,Supuestos!$B$27,0) | F8: =H7 | G8: =IF(L8>0.01,MIN(Supuestos!$B$13,L8+M8+N8),0) | H8: =Supuestos!$B$24+IF(A8<=Supuestos!$B$26,Supuestos!$B$25,0) | I8: =B8+C8+D8-E8-F8-G8-H8 | J8: =MAX(0,MIN(I8,L8+M8+N8-G8)) | K8: =B8+C8+D8-E8-F8-G8-J8 | L8: =O7 | M8: =L8*Supuestos!$B$18 | N8: =IF(L8>0.01,Supuestos!$B$15,0) | O8: =L8+M8+N8-G8-J8 | P8: =P7+M8
A9: =DATE(YEAR(A8),MONTH(A8)+1,1) | B9: =K8 | C9: =Supuestos!$B$8 | D9: =0 | E9: =Supuestos!$B$31+Supuestos!$B$32+Supuestos!$B$33+Supuestos!$B$34+IF(A9<=Supuestos!$B$28,Supuestos!$B$27,0) | F9: =H8 | G9: =IF(L9>0.01,MIN(Supuestos!$B$13,L9+M9+N9),0) | H9: =Supuestos!$B$24+IF(A9<=Supuestos!$B$26,Supuestos!$B$25,0) | I9: =B9+C9+D9-E9-F9-G9-H9 | J9: =MAX(0,MIN(I9,L9+M9+N9-G9)) | K9: =B9+C9+D9-E9-F9-G9-J9 | L9: =O8 | M9: =L9*Supuestos!$B$18 | N9: =IF(L9>0.01,Supuestos!$B$15,0) | O9: =L9+M9+N9-G9-J9 | P9: =P8+M9
A10: =DATE(YEAR(A9),MONTH(A9)+1,1) | B10: =K9 | C10: =Supuestos!$B$8 | D10: =0 | E10: =Supuestos!$B$31+Supuestos!$B$32+Supuestos!$B$33+Supuestos!$B$34+IF(A10<=Supuestos!$B$28,Supuestos!$B$27,0) | F10: =H9 | G10: =IF(L10>0.01,MIN(Supuestos!$B$13,L10+M10+N10),0) | H10: =Supuestos!$B$24+IF(A10<=Supuestos!$B$26,Supuestos!$B$25,0) | I10: =B10+C10+D10-E10-F10-G10-H10 | J10: =MAX(0,MIN(I10,L10+M10+N10-G10)) | K10: =B10+C10+D10-E10-F10-G10-J10 | L10: =O9 | M10: =L10*Supuestos!$B$18 | N10: =IF(L10>0.01,Supuestos!$B$15,0) | O10: =L10+M10+N10-G10-J10 | P10: =P9+M10
A11: =DATE(YEAR(A10),MONTH(A10)+1,1) | B11: =K10 | C11: =Supuestos!$B$8 | D11: =0 | E11: =Supuestos!$B$31+Supuestos!$B$32+Supuestos!$B$33+Supuestos!$B$34+IF(A11<=Supuestos!$B$28,Supuestos!$B$27,0) | F11: =H10 | G11: =IF(L11>0.01,MIN(Supuestos!$B$13,L11+M11+N11),0) | H11: =Supuestos!$B$24+IF(A11<=Supuestos!$B$26,Supuestos!$B$25,0) | I11: =B11+C11+D11-E11-F11-G11-H11 | J11: =MAX(0,MIN(I11,L11+M11+N11-G11)) | K11: =B11+C11+D11-E11-F11-G11-J11 | L11: =O10 | M11: =L11*Supuestos!$B$18 | N11: =IF(L11>0.01,Supuestos!$B$15,0) | O11: =L11+M11+N11-G11-J11 | P11: =P10+M11
A12: =DATE(YEAR(A11),MONTH(A11)+1,1) | B12: =K11 | C12: =Supuestos!$B$8 | D12: =0 | E12: =Supuestos!$B$31+Supuestos!$B$32+Supuestos!$B$33+Supuestos!$B$34+IF(A12<=Supuestos!$B$28,Supuestos!$B$27,0) | F12: =H11 | G12: =IF(L12>0.01,MIN(Supuestos!$B$13,L12+M12+N12),0) | H12: =Supuestos!$B$24+IF(A12<=Supuestos!$B$26,Supuestos!$B$25,0) | I12: =B12+C12+D12-E12-F12-G12-H12 | J12: =MAX(0,MIN(I12,L12+M12+N12-G12)) | K12: =B12+C12+D12-E12-F12-G12-J12 | L12: =O11 | M12: =L12*Supuestos!$B$18 | N12: =IF(L12>0.01,Supuestos!$B$15,0) | O12: =L12+M12+N12-G12-J12 | P12: =P11+M12
A13: =DATE(YEAR(A12),MONTH(A12)+1,1) | B13: =K12 | C13: =Supuestos!$B$8 | D13: =0 | E13: =Supuestos!$B$31+Supuestos!$B$32+Supuestos!$B$33+Supuestos!$B$34+IF(A13<=Supuestos!$B$28,Supuestos!$B$27,0) | F13: =H12 | G13: =IF(L13>0.01,MIN(Supuestos!$B$13,L13+M13+N13),0) | H13: =Supuestos!$B$24+IF(A13<=Supuestos!$B$26,Supuestos!$B$25,0) | I13: =B13+C13+D13-E13-F13-G13-H13 | J13: =MAX(0,MIN(I13,L13+M13+N13-G13)) | K13: =B13+C13+D13-E13-F13-G13-J13 | L13: =O12 | M13: =L13*Supuestos!$B$18 | N13: =IF(L13>0.01,Supuestos!$B$15,0) | O13: =L13+M13+N13-G13-J13 | P13: =P12+M13
A15: Mes en que la deuda llega a 0 | B15: =IFERROR(INDEX(A5:A13,MATCH(TRUE,INDEX(O5:O13<0.01,0),0)),"Después")
A16: Intereses totales del ExtraCash | B16: =SUM(M5:M13)
A17: Nota: caja final incluye lo apartado para la tarjeta del mes siguiente.
